mym2m/__init__.py
mym2m/exceptions.py
mym2m/mym2m.py
mym2m/snapshot.py
mym2m_client-0.1.0.dist-info/DESCRIPTION.rst
mym2m_client-0.1.0.dist-info/METADATA
mym2m_client-0.1.0.dist-info/RECORD
mym2m_client-0.1.0.dist-info/WHEEL
mym2m_client-0.1.0.dist-info/metadata.json
mym2m_client-0.1.0.dist-info/top_level.txt
