Metadata-Version: 2.0
Name: mym2m-client
Version: 0.1.0
Summary: Python SDK for the MyM2M Web JSON Device API
Home-page: https://bitbucket.org/360telemetry/mym2m-python-sdk
Author: 360 Telemetry
Author-email: info@360telemetry.com
License: MIT
Platform: UNKNOWN
Requires-Dist: requests
